LICENSE
MANIFEST.in
README.rst
setup.cfg
setup.py
tests/test_wGNMF.py
tests/test_wNMF.py
wNMFx/__init__.py
wNMFx/wNMF.py
wNMFx.egg-info/PKG-INFO
wNMFx.egg-info/SOURCES.txt
wNMFx.egg-info/dependency_links.txt
wNMFx.egg-info/requires.txt
wNMFx.egg-info/top_level.txt